plwordnet/__init__.py
plwordnet/display.py
plwordnet/domains.py
plwordnet/wordnet.py
plwordnet-0.1.5.dist-info/LICENSE
plwordnet-0.1.5.dist-info/METADATA
plwordnet-0.1.5.dist-info/WHEEL
plwordnet-0.1.5.dist-info/top_level.txt
plwordnet-0.1.5.dist-info/RECORD
