Metadata-Version: 2.1
Name: plwordnet
Version: 0.1.5
Summary: Library for using the Polish Wordnet in the plwnxml format
Home-page: https://github.com/maxadamski/plwordnet
Author: Max Adamski
Author-email: max@maxadamski.com
License: MIT
Platform: UNKNOWN
Classifier: License :: OSI Approved :: MIT License
Classifier: Programming Language :: Python :: 3
Classifier: Programming Language :: Python :: 3.7
Classifier: Programming Language :: Python :: 3.8
Classifier: Programming Language :: Python :: 3.9
Classifier: Natural Language :: Polish
Requires-Python: >=3.7
License-File: LICENSE
